local_simple_database/__init__.py
local_simple_database/class_dict_database_handler.py
local_simple_database/class_local_dict_database.py
local_simple_database/class_local_simple_database.py
local_simple_database/virtual_class_all_local_databases.py
local_simple_database-0.1.8.dist-info/AUTHORS.rst
local_simple_database-0.1.8.dist-info/LICENSE.txt
local_simple_database-0.1.8.dist-info/METADATA
local_simple_database-0.1.8.dist-info/WHEEL
local_simple_database-0.1.8.dist-info/top_level.txt
local_simple_database-0.1.8.dist-info/RECORD
